{
	"pic":[
		{"url":"images/41.JPEG", "longitude":"20", "latitude":"20"},
		{"url":"images/42.JPEG", "longitude":"20", "latitude":"20"},
		{"url":"images/43.JPEG", "longitude":"20", "latitude":"20"},
		{"url":"images/44.JPEG", "longitude":"20", "latitude":"20"},
		{"url":"images/45.JPEG", "longitude":"20", "latitude":"20"},
		{"url":"images/46.JPEG", "longitude":"20", "latitude":"20"},
		{"url":"images/47.JPEG", "longitude":"20", "latitude":"20"},
		{"url":"images/48.JPEG", "longitude":"20", "latitude":"20"},
		{"url":"images/49.JPEG", "longitude":"20", "latitude":"20"},
		{"url":"images/50.JPEG", "longitude":"20", "latitude":"20"}
	]
}